Metadata-Version: 2.1
Name: opencage
Version: 3.0.3
Summary: Wrapper module for the OpenCage Geocoder API
Home-page: https://github.com/OpenCageData/python-opencage-geocoder/
Download-URL: https://github.com/OpenCageData/python-opencage-geocoder/tarball/3.0.3
Author: OpenCage GmbH
Author-email: info@opencagedata.com
License: BSD
Keywords: geocoding,geocoder
Classifier: Environment :: Web Environment
Classifier: Development Status :: 5 - Production/Stable
Classifier: Intended Audience :: Developers
Classifier: License :: OSI Approved :: BSD License
Classifier: Operating System :: OS Independent
Classifier: Programming Language :: Python :: 3 :: Only
Classifier: Programming Language :: Python :: 3.8
Classifier: Programming Language :: Python :: 3.9
Classifier: Programming Language :: Python :: 3.10
Classifier: Programming Language :: Python :: 3.11
Classifier: Programming Language :: Python :: 3.12
Classifier: Programming Language :: Python :: 3.13
Classifier: Topic :: Scientific/Engineering :: GIS
Classifier: Topic :: Utilities
License-File: LICENSE.txt
Requires-Dist: Requests>=2.31.0
Requires-Dist: backoff>=2.2.1
Requires-Dist: tqdm>=4.66.4
Requires-Dist: certifi>=2024.07.04
Requires-Dist: aiohttp>=3.10.5
